awsfile_helper/__init__.py
awsfile_helper/bp/__init__.py
awsfile_helper/bp/aws_api.py
awsfile_helper/dmo/__init__.py
awsfile_helper/dmo/credential_manager.py
awsfile_helper/dmo/file_content_reader.py
awsfile_helper/dmo/file_content_writer.py
awsfile_helper/dmo/s3_bucket_reader.py
awsfile_helper/dmo/s3_image_writer.py
awsfile_helper/find_jpg_file.py
awsfile_helper/find_owl_file.py
awsfile_helper/find_s3_file.py
awsfile_helper/svc/__init__.py
awsfile_helper/svc/connect_to_s3.py
awsfile_helper/svc/create_bucket_folder.py
awsfile_helper/svc/download_from_s3.py
awsfile_helper/svc/find_file_by_version.py
awsfile_helper/svc/find_latest_version_number.py
awsfile_helper/svc/invoke_rekognition_labeler.py
awsfile_helper/svc/invoke_textract_api.py
awsfile_helper/svc/read_from_cache.py
awsfile_helper/svc/read_from_s3.py
awsfile_helper/svc/upload_image_files.py
awsfile_helper-0.1.18.dist-info/METADATA
awsfile_helper-0.1.18.dist-info/WHEEL
awsfile_helper-0.1.18.dist-info/RECORD
