Metadata-Version: 2.1
Name: awsfile-helper
Version: 0.1.18
Summary: AWS File Helper for Easier I/O
Home-page: https://github.com/craigtrim/awsfile-helper
License: None
Keywords: aws,cloud,s3,bucket,helper,utility
Author: Craig Trim
Author-email: craigtrim@gmail.com
Maintainer: Craig Trim
Maintainer-email: craigtrim@gmail.com
Requires-Python: >=3.8.5,<4.0.0
Classifier: Development Status :: 4 - Beta
Classifier: License :: Other/Proprietary License
Classifier: Programming Language :: Python :: 3
Classifier: Programming Language :: Python :: 3.9
Classifier: Programming Language :: Python :: 3.10
Classifier: Programming Language :: Python :: 3.11
Classifier: Topic :: Scientific/Engineering :: Artificial Intelligence
Classifier: Topic :: Software Development :: Libraries :: Python Modules
Requires-Dist: baseblock
Requires-Dist: boto3 (==1.28.11)
Project-URL: Bug Tracker, https://github.com/craigtrim/awsfile-helper/issues
Project-URL: Repository, https://github.com/craigtrim/awsfile-helper
